LICENSE.txt
MANIFEST.in
README.md
setup.cfg
setup.py
peitho/__init__.py
peitho.egg-info/PKG-INFO
peitho.egg-info/SOURCES.txt
peitho.egg-info/dependency_links.txt
peitho.egg-info/entry_points.txt
peitho.egg-info/not-zip-safe
peitho.egg-info/requires.txt
peitho.egg-info/top_level.txt
peitho/errors_and_parsers/__init__.py
peitho/errors_and_parsers/abc_sysbio/__init__.py
peitho/errors_and_parsers/abc_sysbio/abcsysbio/__init__.py
peitho/errors_and_parsers/abc_sysbio/abcsysbio/checkInputArguments.py
peitho/errors_and_parsers/abc_sysbio/abcsysbio/generateTemplate.py
peitho/errors_and_parsers/abc_sysbio/abcsysbio/relations.py
peitho/errors_and_parsers/abc_sysbio/abcsysbio_parser/CUDAParser.py
peitho/errors_and_parsers/abc_sysbio/abcsysbio_parser/CWriter.py
peitho/errors_and_parsers/abc_sysbio/abcsysbio_parser/CandPythonParser.py
peitho/errors_and_parsers/abc_sysbio/abcsysbio_parser/GillespieCUDAWriter.py
peitho/errors_and_parsers/abc_sysbio/abcsysbio_parser/GillespiePythonWriter.py
peitho/errors_and_parsers/abc_sysbio/abcsysbio_parser/ODECUDAParser.py
peitho/errors_and_parsers/abc_sysbio/abcsysbio_parser/ODECUDAWriter.py
peitho/errors_and_parsers/abc_sysbio/abcsysbio_parser/ODEPythonWriter.py
peitho/errors_and_parsers/abc_sysbio/abcsysbio_parser/ParseAndWrite.py
peitho/errors_and_parsers/abc_sysbio/abcsysbio_parser/ParsedModel.py
peitho/errors_and_parsers/abc_sysbio/abcsysbio_parser/Parser.py
peitho/errors_and_parsers/abc_sysbio/abcsysbio_parser/SDEAndGillespieCUDAParser.py
peitho/errors_and_parsers/abc_sysbio/abcsysbio_parser/SDECUDAWriter.py
peitho/errors_and_parsers/abc_sysbio/abcsysbio_parser/SDEPythonWriter.py
peitho/errors_and_parsers/abc_sysbio/abcsysbio_parser/Writer.py
peitho/errors_and_parsers/abc_sysbio/abcsysbio_parser/__init__.py
peitho/errors_and_parsers/error_checks/SBML_check.py
peitho/errors_and_parsers/error_checks/__init__.py
peitho/errors_and_parsers/error_checks/error_check.py
peitho/errors_and_parsers/ode_parsers/SBML_reactions.py
peitho/errors_and_parsers/ode_parsers/__init__.py
peitho/errors_and_parsers/ode_parsers/cudacodecreater.py
peitho/errors_and_parsers/ode_parsers/input_data_file_parser.py
peitho/errors_and_parsers/ode_parsers/parse_object_info.py
