Metadata-Version: 1.1
Name: peitho
Version: 0.1.3
Summary: Perfecting Experiments with Information Theory
Home-page: https://github.com/MichaelPHStumpf/Peitho
Author: Leander Dony, Scott Ward, Jonas Mackerodt, Juliane Liepe, Michael PH Stumpf
Author-email: m.stumpf@imperial.ac.uk
License: MIT
Download-URL: https://github.com/MichaelPHStumpf/Peitho/archive/0.1.3.tar.gz
Keywords: information theory,entropy,experimental design
Platform: UNKNOWN
Classifier: Development Status :: 3 - Alpha
Classifier: Environment :: Console
Classifier: Intended Audience :: Science/Research
Classifier: Topic :: Scientific/Engineering :: Bio-Informatics
Classifier: License :: OSI Approved :: MIT License
Classifier: Programming Language :: Python :: 2.7
